microdrop/__init__.py
microdrop/__init__.pyc
microdrop/__main__.py
microdrop/app.py
microdrop/app.pyc
microdrop/app_context.py
microdrop/app_context.pyc
microdrop/config.py
microdrop/config.pyc
microdrop/dmf_device.py
microdrop/dmf_device.pyc
microdrop/experiment_log.py
microdrop/experiment_log.pyc
microdrop/interfaces.py
microdrop/interfaces.pyc
microdrop/logger.py
microdrop/logger.pyc
microdrop/microdrop.ico
microdrop/microdrop.py
microdrop/plugin_helpers.py
microdrop/plugin_helpers.pyc
microdrop/plugin_manager.py
microdrop/plugin_manager.pyc
microdrop/protocol.py
microdrop/protocol.pyc
microdrop/requirements.txt
microdrop/bin/__init__.py
microdrop/bin/__init__.pyc
microdrop/bin/create_portable_config.py
microdrop/bin/latest_versions.py
microdrop/devices/DMF-90-pin-array/device
microdrop/gui/__init__.py
microdrop/gui/__init__.pyc
microdrop/gui/app_options_controller.py
microdrop/gui/app_options_controller.pyc
microdrop/gui/config_controller.py
microdrop/gui/config_controller.pyc
microdrop/gui/dmf_device_controller.py
microdrop/gui/dmf_device_controller.pyc
microdrop/gui/dmf_device_view.py
microdrop/gui/dmf_device_view.pyc
microdrop/gui/experiment_log_controller.py
microdrop/gui/experiment_log_controller.pyc
microdrop/gui/field_filter_controller.py
microdrop/gui/main_window_controller.py
microdrop/gui/main_window_controller.pyc
microdrop/gui/plugin_download_dialog.py
microdrop/gui/plugin_download_dialog.pyc
microdrop/gui/plugin_manager_controller.py
microdrop/gui/plugin_manager_controller.pyc
microdrop/gui/plugin_manager_dialog.py
microdrop/gui/plugin_manager_dialog.pyc
microdrop/gui/protocol_controller.py
microdrop/gui/protocol_controller.pyc
microdrop/gui/protocol_grid_controller.py
microdrop/gui/protocol_grid_controller.pyc
microdrop/gui/.ropeproject/config.py
microdrop/gui/.ropeproject/globalnames
microdrop/gui/.ropeproject/history
microdrop/gui/.ropeproject/objectdb
microdrop-1.0.post74.dist-info/DESCRIPTION.rst
microdrop-1.0.post74.dist-info/METADATA
microdrop-1.0.post74.dist-info/RECORD
microdrop-1.0.post74.dist-info/WHEEL
microdrop-1.0.post74.dist-info/metadata.json
microdrop-1.0.post74.dist-info/pbr.json
microdrop-1.0.post74.dist-info/top_level.txt
